iphyre/__init__.py
iphyre/games.py
iphyre/simulator.py
iphyre/utils.py
iphyre-0.2.1.dist-info/LICENSE
iphyre-0.2.1.dist-info/METADATA
iphyre-0.2.1.dist-info/WHEEL
iphyre-0.2.1.dist-info/top_level.txt
iphyre-0.2.1.dist-info/RECORD
