Metadata-Version: 2.1
Name: iphyre
Version: 0.2.1
Summary: Benchmark for Interactive Physical Reasoning
Author: CoRe
Project-URL: Homepage, https://lishiqianhugh.github.io/IPHYRE/
Classifier: Programming Language :: Python :: 3.10
Classifier: License :: OSI Approved :: MIT License
Classifier: Operating System :: OS Independent
Requires-Python: >=3.8
License-File: LICENSE
